ez_setup.py
setup.cfg
setup.py
grizzled/__init__.py
grizzled/cmdline.py
grizzled/config.py
grizzled/decorators.py
grizzled/exception.py
grizzled/history.py
grizzled/log.py
grizzled/misc.py
grizzled/os.py
grizzled/system.py
grizzled.egg-info/PKG-INFO
grizzled.egg-info/SOURCES.txt
grizzled.egg-info/dependency_links.txt
grizzled.egg-info/top_level.txt
grizzled/collections/__init__.py
grizzled/collections/dict.py
grizzled/collections/tuple.py
grizzled/db/__init__.py
grizzled/db/base.py
grizzled/db/dbgadfly.py
grizzled/db/dummydb.py
grizzled/db/mysql.py
grizzled/db/oracle.py
grizzled/db/postgresql.py
grizzled/db/sqlite.py
grizzled/db/sqlserver.py
grizzled/file/__init__.py
grizzled/file/includer.py
grizzled/io/__init__.py
grizzled/io/filelock.py
grizzled/net/__init__.py
grizzled/net/ftp/__init__.py
grizzled/net/ftp/parse.py
grizzled/text/__init__.py
test/__init__.py
test/collections/TestLRUDict.py
test/collections/__init__.py
test/config/TestConfiguration.py
test/config/__init__.py
test/file/Test.py
test/file/__init__.py
test/io/TestPushback.py
test/io/__init__.py
test/system/Test.py
test/system/__init__.py
test/text/TestStr2Bool.py
test/text/__init__.py