Metadata-Version: 1.0
Name: grizzled
Version: 0.9.4
Summary: The Grizzled Python Utility Library
Home-page: http://bmc.github.com/grizzled/
Author: Brian M. Clapper
Author-email: bmc@clapper.org
License: 0.9.4
Platform: UNKNOWN
Classifier: Intended Audience :: Developers
Classifier: License :: OSI Approved :: BSD License
Classifier: Programming Language :: Python
Classifier: Topic :: Software Development :: Libraries
Classifier: Topic :: Software Development :: Libraries :: Python Modules
